futhark_ffi/__init__.py
futhark_ffi/build.py
futhark_ffi/compat.py
futhark_ffi-0.16.0.dist-info/LICENSE
futhark_ffi-0.16.0.dist-info/METADATA
futhark_ffi-0.16.0.dist-info/WHEEL
futhark_ffi-0.16.0.dist-info/entry_points.txt
futhark_ffi-0.16.0.dist-info/top_level.txt
futhark_ffi-0.16.0.dist-info/RECORD
