Metadata-Version: 2.1
Name: futhark-ffi
Version: 0.16.0
Summary: A Python library using the Futhark C backend via CFFI 
Home-page: https://github.com/pepijndevos/futhark-pycffi
Author: Pepijn de Vos
License: UNKNOWN
Platform: UNKNOWN
License-File: LICENSE
Requires-Dist: numpy
Requires-Dist: cffi
